bltm/__init__.py
bltm/bltm.cpython-36m-x86_64-linux-gnu.so
bltm-0.3.dist-info/METADATA
bltm-0.3.dist-info/WHEEL
bltm-0.3.dist-info/top_level.txt
bltm-0.3.dist-info/RECORD
